GoYuyanGaoxingnengBianchengFix1/README.md
GoYuyanGaoxingnengBianchengFix1/__init__.py
GoYuyanGaoxingnengBianchengFix1/__main__.py
GoYuyanGaoxingnengBianchengFix1/file.epub
GoYuyanGaoxingnengBianchengFix1/index.html
GoYuyanGaoxingnengBianchengFix1/css/__init__.py
GoYuyanGaoxingnengBianchengFix1/css/annotations.css
GoYuyanGaoxingnengBianchengFix1/css/main.css
GoYuyanGaoxingnengBianchengFix1/css/normalize.css
GoYuyanGaoxingnengBianchengFix1/css/popup.css
GoYuyanGaoxingnengBianchengFix1/font/__init__.py
GoYuyanGaoxingnengBianchengFix1/font/fontello.eot
GoYuyanGaoxingnengBianchengFix1/font/fontello.svg
GoYuyanGaoxingnengBianchengFix1/font/fontello.ttf
GoYuyanGaoxingnengBianchengFix1/font/fontello.woff
GoYuyanGaoxingnengBianchengFix1/img/__init__.py
GoYuyanGaoxingnengBianchengFix1/img/annotator-glyph-sprite.png
GoYuyanGaoxingnengBianchengFix1/img/annotator-icon-sprite.png
GoYuyanGaoxingnengBianchengFix1/img/apple-touch-icon.png
GoYuyanGaoxingnengBianchengFix1/img/cancelfullscreen.png
GoYuyanGaoxingnengBianchengFix1/img/close.png
GoYuyanGaoxingnengBianchengFix1/img/fullscreen.png
GoYuyanGaoxingnengBianchengFix1/img/loader.gif
GoYuyanGaoxingnengBianchengFix1/img/menu-icon.png
GoYuyanGaoxingnengBianchengFix1/img/save.png
GoYuyanGaoxingnengBianchengFix1/img/saved.png
GoYuyanGaoxingnengBianchengFix1/img/settings-s.png
GoYuyanGaoxingnengBianchengFix1/img/settings.png
GoYuyanGaoxingnengBianchengFix1/img/star.png
GoYuyanGaoxingnengBianchengFix1/js/__init__.py
GoYuyanGaoxingnengBianchengFix1/js/epub.js
GoYuyanGaoxingnengBianchengFix1/js/epub.min.js
GoYuyanGaoxingnengBianchengFix1/js/epub.min.map
GoYuyanGaoxingnengBianchengFix1/js/hooks.min.js
GoYuyanGaoxingnengBianchengFix1/js/hooks.min.map
GoYuyanGaoxingnengBianchengFix1/js/reader.js
GoYuyanGaoxingnengBianchengFix1/js/reader.js.map
GoYuyanGaoxingnengBianchengFix1/js/reader.min.js
GoYuyanGaoxingnengBianchengFix1/js/reader.min.map
GoYuyanGaoxingnengBianchengFix1/js/hooks/__init__.py
go_yuyan_gaoxingneng_biancheng_fix1-2025.3.25.1.dist-info/METADATA
go_yuyan_gaoxingneng_biancheng_fix1-2025.3.25.1.dist-info/WHEEL
go_yuyan_gaoxingneng_biancheng_fix1-2025.3.25.1.dist-info/entry_points.txt
go_yuyan_gaoxingneng_biancheng_fix1-2025.3.25.1.dist-info/top_level.txt
go_yuyan_gaoxingneng_biancheng_fix1-2025.3.25.1.dist-info/RECORD
